fluidattacks_gitlab_sdk/__init__.py
fluidattacks_gitlab_sdk/_decoders.py
fluidattacks_gitlab_sdk/_handlers.py
fluidattacks_gitlab_sdk/_logger.py
fluidattacks_gitlab_sdk/ids.py
fluidattacks_gitlab_sdk/py.typed
fluidattacks_gitlab_sdk/_gql_client/__init__.py
fluidattacks_gitlab_sdk/_gql_client/_client.py
fluidattacks_gitlab_sdk/_gql_client/_error.py
fluidattacks_gitlab_sdk/_gql_client/_handlers.py
fluidattacks_gitlab_sdk/_http_client/__init__.py
fluidattacks_gitlab_sdk/_http_client/_client_1.py
fluidattacks_gitlab_sdk/_http_client/_core.py
fluidattacks_gitlab_sdk/issues/__init__.py
fluidattacks_gitlab_sdk/issues/core.py
fluidattacks_gitlab_sdk/issues/_client/__init__.py
fluidattacks_gitlab_sdk/issues/_client/_decode.py
fluidattacks_gitlab_sdk/issues/_client/_get_issue.py
fluidattacks_gitlab_sdk/issues/_client/_most_recent.py
fluidattacks_gitlab_sdk/issues/_client/_updated_by.py
fluidattacks_gitlab_sdk/jobs/__init__.py
fluidattacks_gitlab_sdk/jobs/_client.py
fluidattacks_gitlab_sdk/jobs/_decode.py
fluidattacks_gitlab_sdk/jobs/core.py
fluidattacks_gitlab_sdk/members/__init__.py
fluidattacks_gitlab_sdk/members/_client.py
fluidattacks_gitlab_sdk/members/_decode.py
fluidattacks_gitlab_sdk/members/core.py
fluidattacks_gitlab_sdk/merge_requests/__init__.py
fluidattacks_gitlab_sdk/merge_requests/_client.py
fluidattacks_gitlab_sdk/merge_requests/_decode.py
fluidattacks_gitlab_sdk/merge_requests/core.py
fluidattacks_gitlab_sdk/milestones/__init__.py
fluidattacks_gitlab_sdk/milestones/_client.py
fluidattacks_gitlab_sdk/milestones/_decode.py
fluidattacks_gitlab_sdk/milestones/core.py
fluidattacks_gitlab_sdk/mr_approvals/__init__.py
fluidattacks_gitlab_sdk/mr_approvals/_client.py
fluidattacks_gitlab_sdk/mr_approvals/_decode.py
fluidattacks_gitlab_sdk/mr_approvals/core.py
fluidattacks_gitlab_sdk/users/__init__.py
fluidattacks_gitlab_sdk/users/core.py
fluidattacks_gitlab_sdk/users/decode.py
fluidattacks_gitlab_sdk-2.2.0.dist-info/WHEEL
fluidattacks_gitlab_sdk-2.2.0.dist-info/METADATA
fluidattacks_gitlab_sdk-2.2.0.dist-info/RECORD
