Metadata-Version: 2.4
Name: fluidattacks_gitlab_sdk
Version: 2.2.0
Summary: gitlab SDK
Author-email: Product Team <development@fluidattacks.com>
Requires-Python: >=3.11
Requires-Dist: gql >=3.5.0, <4.0.0
Requires-Dist: requests-toolbelt >=1.0.0, <2.0.0
Requires-Dist: fa-purity >=2.5.2, <3.0.0
Requires-Dist: pure-requests >=3.0.0, <4.0.0
Requires-Dist: python-dateutil >=2.8.0, <3.0.0
Requires-Dist: fluidattacks-etl-utils >=2.0.0, <3.0.0
Requires-Dist: fluidattacks-utils-logger >=3.0.0, <4.0.0
